simple_preprocessing/__init__.py
simple_preprocessing/encoder_switcher.py
simple_preprocessing-0.0.5.dist-info/METADATA
simple_preprocessing-0.0.5.dist-info/WHEEL
simple_preprocessing-0.0.5.dist-info/top_level.txt
simple_preprocessing-0.0.5.dist-info/RECORD
